PPshare/__init__.py
PPshare/datasets.py
PPshare/air/__init__.py
PPshare/air/air_hebei.py
PPshare/air/air_zhenqi.py
PPshare/air/cons.py
PPshare/air/crypto.js
PPshare/air/outcrypto.js
PPshare/air/sunrise_tad.py
PPshare/article/__init__.py
PPshare/article/cons.py
PPshare/article/epu_index.py
PPshare/article/ff_factor.py
PPshare/article/fred_md.py
PPshare/article/risk_rv.py
PPshare/bank/__init__.py
PPshare/bank/bank_cbirc_2020.py
PPshare/bank/cons.py
PPshare/bond/__init__.py
PPshare/bond/bond_bank.py
PPshare/bond/bond_cbond.py
PPshare/bond/bond_china_money.py
PPshare/bond/bond_convert.py
PPshare/bond/bond_em.py
PPshare/bond/bond_futures.py
PPshare/bond/bond_info_cm.py
PPshare/bond/bond_investing.py
PPshare/bond/bond_issue_cninfo.py
PPshare/bond/bond_summary.py
PPshare/bond/bond_zh_cov_sina.py
PPshare/bond/bond_zh_sina.py
PPshare/bond/china_bond.py
PPshare/bond/china_repo.py
PPshare/bond/cons.py
PPshare/cost/__init__.py
PPshare/cost/cost_living.py
PPshare/crypto/__init__.py
PPshare/crypto/crypto_bitcoin_cme.py
PPshare/crypto/crypto_crix.py
PPshare/crypto/crypto_hist_investing.py
PPshare/crypto/crypto_hold.py
PPshare/currency/__init__.py
PPshare/currency/currency.py
PPshare/currency/currency_china_bank_sina.py
PPshare/currency/currency_safe.py
PPshare/data/__init__.py
PPshare/data/covid.js
PPshare/data/crypto_info.zip
PPshare/data/ths.js
PPshare/economic/__init__.py
PPshare/economic/cons.py
PPshare/economic/macro_australia.py
PPshare/economic/macro_bank.py
PPshare/economic/macro_canada.py
PPshare/economic/macro_china.py
PPshare/economic/macro_china_hk.py
PPshare/economic/macro_constitute.py
PPshare/economic/macro_euro.py
PPshare/economic/macro_germany.py
PPshare/economic/macro_japan.py
PPshare/economic/macro_other.py
PPshare/economic/macro_swiss.py
PPshare/economic/macro_uk.py
PPshare/economic/macro_usa.py
PPshare/economic/marco_cnbs.py
PPshare/energy/__init__.py
PPshare/energy/energy_carbon.py
PPshare/energy/energy_oil_em.py
PPshare/event/__init__.py
PPshare-1.1.6.dist-info/LICENSE
PPshare-1.1.6.dist-info/METADATA
PPshare-1.1.6.dist-info/WHEEL
PPshare-1.1.6.dist-info/top_level.txt
PPshare-1.1.6.dist-info/RECORD
