Metadata-Version: 2.1
Name: PPshare
Version: 1.1.6
Summary: PPshare is an application platform that focuses on scientific research data for a long time. The platform provides direct crawling from the Internet, community collection, and team collation of data and storage into a database. It provides users with high-quality scientific research data through strict control over data quality.
Home-page: https://github.com/zemengchuan/PPshare
Author: zemengchuan
Author-email: zemengchuan@gmail.com
License: MIT
Keywords: macro,webcrawler,data
Classifier: Programming Language :: Python :: 3.7
Classifier: Programming Language :: Python :: 3.8
Classifier: Programming Language :: Python :: 3.9
Classifier: Programming Language :: Python :: 3.10
Classifier: Programming Language :: Python :: 3.11
Classifier: License :: OSI Approved :: MIT License
Classifier: Operating System :: OS Independent
Requires-Python: >=3.7
License-File: LICENSE
Requires-Dist: beautifulsoup4 (>=4.9.1)
Requires-Dist: lxml (>=4.2.1)
Requires-Dist: pandas (>=0.25)
Requires-Dist: requests (>=2.22.0)
Requires-Dist: pypinyin (>=0.35.0)
Requires-Dist: websocket-client (>=0.56.0)
Requires-Dist: html5lib (>=1.0.1)
Requires-Dist: xlrd (>=1.2.0)
Requires-Dist: urllib3 (>=1.25.8)
Requires-Dist: tqdm (>=4.43.0)
Requires-Dist: openpyxl (>=3.0.3)
Requires-Dist: jsonpath (>=0.82)
Requires-Dist: tabulate (>=0.8.6)
Requires-Dist: decorator (>=4.4.2)
Requires-Dist: py-mini-racer (>=0.6.0)
Requires-Dist: requests-cache (>=0.9.3)
Requires-Dist: cfscrape (>=2.1.1)
Requires-Dist: fuzzywuzzy (>=0.18.0)
